{"id": "soporific", "metadata": {"operation": "retrieve", "provider": "Oxford University Press", "schema": "RetrieveEntry"}, "results": [{"id": "soporific", "language": "en-gb", "lexicalEntries": [{"derivatives": [{"id": "soporifically", "text": "soporifically"}], "entries": [{"etymologies": ["mid 17th century: from Latin sopor \u2018sleep\u2019 + -fic"], "pronunciations": [{"audioFile": "https://audio.oxforddictionaries.com/en/mp3/soporific_gb_1.mp3", "dialects": ["British English"], "phoneticNotation": "IPA", "phoneticSpelling": "\u02ccs\u0252p\u0259\u02c8r\u026af\u026ak"}], "senses": [{"definitions": ["tending to induce drowsiness or sleep"], "examples": [{"text": "the motion of the train had a somewhat soporific effect"}], "id": "m_en_gbus0969020.007", "shortDefinitions": ["tending to induce drowsiness or sleep"], "subsenses": [{"definitions": ["sleepy or drowsy"], "examples": [{"text": "some medicine made her soporific"}], "id": "m_en_gbus0969020.009", "shortDefinitions": ["sleepy or drowsy"]}, {"definitions": ["tediously boring or monotonous"], "examples": [{"text": "a libel trial is in large parts intensely soporific"}], "id": "m_en_gbus0969020.010", "shortDefinitions": ["tediously boring or monotonous"], "synonyms": [{"language": "en", "text": "sleep-inducing"}, {"language": "en", "text": "somnolent"}, {"language": "en", "text": "sedative"}, {"language": "en", "text": "calmative"}, {"language": "en", "text": "tranquillizing"}, {"language": "en", "text": "narcotic"}, {"language": "en", "text": "opiate"}, {"language": "en", "text": "drowsy"}, {"language": "en", "text": "sleepy"}, {"language": "en", "text": "somniferous"}], "thesaurusLinks": [{"entry_id": "soporific", "sense_id": "t_en_gb0013809.001"}]}]}]}], "language": "en-gb", "lexicalCategory": {"id": "adjective", "text": "Adjective"}, "text": "soporific"}, {"derivatives": [{"id": "soporifically", "text": "soporifically"}], "entries": [{"pronunciations": [{"audioFile": "https://audio.oxforddictionaries.com/en/mp3/soporific_gb_1.mp3", "dialects": ["British English"], "phoneticNotation": "IPA", "phoneticSpelling": "\u02ccs\u0252p\u0259\u02c8r\u026af\u026ak"}], "senses": [{"definitions": ["a drug or other substance that induces drowsiness or sleep."], "domainClasses": [{"id": "pharmaceutics", "text": "Pharmaceutics"}], "id": "m_en_gbus0969020.012", "semanticClasses": [{"id": "sedative", "text": "Sedative"}], "shortDefinitions": ["drug or other substance that induces drowsiness or sleep"], "synonyms": [{"language": "en", "text": "sleeping pill"}, {"language": "en", "text": "sleeping potion"}, {"language": "en", "text": "sedative"}, {"language": "en", "text": "calmative"}, {"language": "en", "text": "tranquillizer"}, {"language": "en", "text": "narcotic"}, {"language": "en", "text": "opiate"}], "thesaurusLinks": [{"entry_id": "soporific", "sense_id": "t_en_gb0013809.002"}]}]}], "language": "en-gb", "lexicalCategory": {"id": "noun", "text": "Noun"}, "text": "soporific"}], "type": "headword", "word": "soporific"}], "word": "soporific"}
