{"id": "decrepitude", "metadata": {"operation": "retrieve", "provider": "Oxford University Press", "schema": "RetrieveEntry"}, "results": [{"id": "decrepitude", "language": "en-gb", "lexicalEntries": [{"entries": [{"grammaticalFeatures": [{"id": "mass", "text": "Mass", "type": "Countability"}], "pronunciations": [{"dialects": ["British English"], "phoneticNotation": "IPA", "phoneticSpelling": "d\u026a\u02c8kr\u025bp\u026at\u0283u\u02d0d"}, {"audioFile": "https://audio.oxforddictionaries.com/en/mp3/decrepitude_gb_1.mp3", "dialects": ["British English"], "phoneticNotation": "IPA", "phoneticSpelling": "d\u026a\u02c8kr\u025bp\u026atju\u02d0d"}], "senses": [{"definitions": ["the state of being decrepit"], "domainClasses": [{"id": "physiology", "text": "Physiology"}], "examples": [{"text": "he had passed directly from middle age into decrepitude"}], "id": "m_en_gbus0257940.006", "semanticClasses": [{"id": "negative_condition", "text": "Negative_Condition"}], "shortDefinitions": ["state of being decrepit"], "synonyms": [{"language": "en", "text": "feebleness"}, {"language": "en", "text": "enfeeblement"}, {"language": "en", "text": "infirmity"}, {"language": "en", "text": "weakness"}, {"language": "en", "text": "frailty"}, {"language": "en", "text": "debilitation"}, {"language": "en", "text": "debility"}, {"language": "en", "text": "sickliness"}, {"language": "en", "text": "incapacitation"}, {"language": "en", "text": "malaise"}, {"language": "en", "text": "dilapidation"}, {"language": "en", "text": "ricketiness"}, {"language": "en", "text": "dereliction"}, {"language": "en", "text": "ruin"}, {"language": "en", "text": "disrepair"}, {"language": "en", "text": "rack and ruin"}, {"language": "en", "text": "decay"}, {"language": "en", "text": "deterioration"}], "thesaurusLinks": [{"entry_id": "decrepitude", "sense_id": "t_en_gb0003529.001"}, {"entry_id": "decrepitude", "sense_id": "t_en_gb0003529.002"}]}]}], "language": "en-gb", "lexicalCategory": {"id": "noun", "text": "Noun"}, "text": "decrepitude"}], "type": "headword", "word": "decrepitude"}], "word": "decrepitude"}
