{"id": "ship", "metadata": {"operation": "retrieve", "provider": "Oxford University Press", "schema": "RetrieveEntry"}, "results": [{"id": "ship", "language": "en-gb", "lexicalEntries": [{"derivatives": [{"id": "shipless", "text": "shipless"}, {"id": "shippable", "text": "shippable"}], "entries": [{"etymologies": ["Old English scip (noun), late Old English scipian (verb), of Germanic origin; related to Dutch schip and German Schiff"], "homographNumber": "100", "pronunciations": [{"audioFile": "https://audio.oxforddictionaries.com/en/mp3/ship_gb_1.mp3", "dialects": ["British English"], "phoneticNotation": "IPA", "phoneticSpelling": "\u0283\u026ap"}], "senses": [{"definitions": ["a large boat for transporting people or goods by sea"], "domainClasses": [{"id": "nautical", "text": "Nautical"}], "examples": [{"text": "the ship left England with a crew of 36"}, {"text": "a cargo ship"}], "id": "m_en_gbus0936160.007", "semanticClasses": [{"id": "boat", "text": "Boat"}], "shortDefinitions": ["large boat for transporting people or goods by sea"], "subsenses": [{"definitions": ["a sailing vessel with a bowsprit and three or more square-rigged masts."], "domainClasses": [{"id": "nautical", "text": "Nautical"}], "id": "m_en_gbus0936160.010", "semanticClasses": [{"id": "boat", "text": "Boat"}], "shortDefinitions": ["sailing vessel with bowsprit and three or more square-rigged masts"]}, {"definitions": ["any boat, especially a racing boat."], "domainClasses": [{"id": "nautical", "text": "Nautical"}], "id": "m_en_gbus0936160.011", "registers": [{"id": "informal", "text": "Informal"}], "semanticClasses": [{"id": "boat", "text": "Boat"}], "shortDefinitions": ["any boat"], "synonyms": [{"language": "en", "text": "ship"}, {"language": "en", "text": "ocean liner"}, {"language": "en", "text": "passenger vessel"}, {"language": "en", "text": "boat"}], "thesaurusLinks": [{"entry_id": "liner", "sense_id": "t_en_gb0008800.001"}]}], "synonyms": [{"language": "en", "text": "vessel"}, {"language": "en", "text": "craft"}, {"language": "en", "text": "boat"}], "thesaurusLinks": [{"entry_id": "ship", "sense_id": "t_en_gb0013376.001"}]}, {"definitions": ["a spaceship."], "domainClasses": [{"id": "space", "text": "Space"}], "id": "m_en_gbus0936160.013", "semanticClasses": [{"id": "spacecraft", "text": "Spacecraft"}], "shortDefinitions": ["spaceship"]}, {"definitions": ["an aircraft."], "domainClasses": [{"id": "aviation", "text": "Aviation"}], "id": "m_en_gbus0936160.015", "regions": [{"id": "north_american", "text": "North_American"}], "semanticClasses": [{"id": "aircraft", "text": "Aircraft"}], "shortDefinitions": ["aircraft"], "synonyms": [{"language": "en", "text": "aircraft"}, {"language": "en", "text": "craft"}, {"language": "en", "text": "flying machine"}], "thesaurusLinks": [{"entry_id": "plane", "sense_id": "t_en_gb0011151.001"}]}]}], "language": "en-gb", "lexicalCategory": {"id": "noun", "text": "Noun"}, "phrasalVerbs": [{"id": "ship_off", "text": "ship off"}], "phrases": [{"id": "a_sinking_ship", "text": "a sinking ship"}, {"id": "ship_a_sea", "text": "ship a sea"}, {"id": "take_ship", "text": "take ship"}, {"id": "that_ship_has_sailed", "text": "that ship has sailed"}, {"id": "when_one%27s_ship_comes_in", "text": "when one's ship comes in"}], "text": "ship"}, {"derivatives": [{"id": "shipless", "text": "shipless"}, {"id": "shippable", "text": "shippable"}], "entries": [{"homographNumber": "101", "inflections": [{"inflectedForm": "ships"}, {"inflectedForm": "shipping"}, {"inflectedForm": "shipped"}], "pronunciations": [{"audioFile": "https://audio.oxforddictionaries.com/en/mp3/ship_gb_1.mp3", "dialects": ["British English"], "phoneticNotation": "IPA", "phoneticSpelling": "\u0283\u026ap"}], "senses": [{"definitions": ["transport (goods or people) on a ship"], "domainClasses": [{"id": "nautical", "text": "Nautical"}], "examples": [{"text": "the wounded soldiers were shipped home"}, {"text": "they agreed to ship the waste out of the country"}], "id": "m_en_gbus0936160.028", "notes": [{"text": "with object and adverbial of direction", "type": "grammaticalNote"}], "shortDefinitions": ["transport goods or people on ship"], "subsenses": [{"definitions": ["send by some other means of transport or by mail"], "examples": [{"text": "the freight would be shipped by rail"}, {"text": "spare parts were quickly shipped out"}], "id": "m_en_gbus0936160.034", "shortDefinitions": ["send by transport or mail"]}, {"definitions": ["(of a product) be made available for purchase"], "domainClasses": [{"id": "electronics", "text": "Electronics"}], "examples": [{"text": "the cellular phone is expected to ship at about $500 sometime this summer"}], "id": "m_en_gbus0936160.035", "notes": [{"text": "no object", "type": "grammaticalNote"}], "shortDefinitions": ["(of product) be made available for purchase"]}, {"definitions": ["(of a naval force) go to sea from a home port"], "examples": [{"text": "Bob got sick a week before we shipped out"}], "id": "m_en_gbus0936160.036", "notes": [{"text": "no object", "type": "grammaticalNote"}, {"text": "\"ship out\"", "type": "wordFormNote"}], "shortDefinitions": ["go to sea from home port"]}, {"definitions": ["embark on a ship"], "domainClasses": [{"id": "nautical", "text": "Nautical"}], "examples": [{"text": "people wishing to get from London to New York ship at Liverpool"}], "id": "m_en_gbus0936160.037", "notes": [{"text": "no object", "type": "grammaticalNote"}], "registers": [{"id": "dated", "text": "Dated"}], "shortDefinitions": ["embark on ship"]}, {"definitions": ["(of a sailor) take service on a ship"], "domainClasses": [{"id": "nautical", "text": "Nautical"}], "examples": [{"text": "Jack, you shipped with the Admiral once, didn't you?"}], "id": "m_en_gbus0936160.038", "shortDefinitions": ["(of sailor) take service on ship"]}], "synonyms": [{"language": "en", "text": "convey"}, {"language": "en", "text": "carry"}, {"language": "en", "text": "take"}, {"language": "en", "text": "transfer"}, {"language": "en", "text": "move"}, {"language": "en", "text": "shift"}, {"language": "en", "text": "bring"}, {"language": "en", "text": "fetch"}, {"language": "en", "text": "send"}, {"language": "en", "text": "deliver"}, {"language": "en", "text": "bear"}, {"language": "en", "text": "conduct"}, {"language": "en", "text": "haul"}, {"language": "en", "text": "lug"}, {"language": "en", "text": "cart"}, {"language": "en", "text": "run"}, {"language": "en", "text": "ship"}, {"language": "en", "text": "ferry"}], "thesaurusLinks": [{"entry_id": "transport", "sense_id": "t_en_gb0015104.001"}]}, {"definitions": ["(of a boat) take in (water) over the side."], "domainClasses": [{"id": "nautical", "text": "Nautical"}], "id": "m_en_gbus0936160.040", "notes": [{"text": "with object", "type": "grammaticalNote"}], "shortDefinitions": ["(of boat) take in water over side"]}, {"definitions": ["take (oars) from the rowlocks and lay them inside a boat."], "domainClasses": [{"id": "rowing", "text": "Rowing"}], "id": "m_en_gbus0936160.042", "notes": [{"text": "with object", "type": "grammaticalNote"}], "shortDefinitions": ["take oars from rowlocks and lay them inside boat"], "subsenses": [{"definitions": ["fix (something such as a rudder or mast) in its place on a boat or ship."], "domainClasses": [{"id": "nautical", "text": "Nautical"}], "id": "m_en_gbus0936160.043", "shortDefinitions": ["fix something in its place on boat or ship"]}]}]}], "language": "en-gb", "lexicalCategory": {"id": "verb", "text": "Verb"}, "phrasalVerbs": [{"id": "ship_off", "text": "ship off"}], "phrases": [{"id": "a_sinking_ship", "text": "a sinking ship"}, {"id": "ship_a_sea", "text": "ship a sea"}, {"id": "take_ship", "text": "take ship"}, {"id": "that_ship_has_sailed", "text": "that ship has sailed"}, {"id": "when_one%27s_ship_comes_in", "text": "when one's ship comes in"}], "text": "ship"}], "type": "headword", "word": "ship"}, {"id": "ship", "language": "en-gb", "lexicalEntries": [{"entries": [{"etymologies": ["early 21st century: abbreviation of relationship"], "homographNumber": "200", "pronunciations": [{"audioFile": "https://audio.oxforddictionaries.com/en/mp3/ship_gb_1.mp3", "dialects": ["British English"], "phoneticNotation": "IPA", "phoneticSpelling": "\u0283\u026ap"}], "senses": [{"definitions": ["a romantic pairing between two characters in a fictional series, often one that is supported or portrayed by fans rather than depicted in the series itself"], "examples": [{"text": "the thing that I loved about the Mulder/Scully ship was that we knew so much about their characters"}], "id": "m_en_gbus0936170.005", "registers": [{"id": "informal", "text": "Informal"}], "semanticClasses": [{"id": "love_affair", "text": "Love_Affair"}], "shortDefinitions": ["romantic pairing between two characters in fictional series"]}]}], "language": "en-gb", "lexicalCategory": {"id": "noun", "text": "Noun"}, "text": "ship"}, {"entries": [{"grammaticalFeatures": [{"id": "intransitive", "text": "Intransitive", "type": "Subcategorization"}], "homographNumber": "201", "inflections": [{"grammaticalFeatures": [{"id": "intransitive", "text": "Intransitive", "type": "Subcategorization"}], "inflectedForm": "ships"}, {"grammaticalFeatures": [{"id": "intransitive", "text": "Intransitive", "type": "Subcategorization"}], "inflectedForm": "shipping"}, {"grammaticalFeatures": [{"id": "intransitive", "text": "Intransitive", "type": "Subcategorization"}], "inflectedForm": "shipped"}], "pronunciations": [{"audioFile": "https://audio.oxforddictionaries.com/en/mp3/ship_gb_1.mp3", "dialects": ["British English"], "phoneticNotation": "IPA", "phoneticSpelling": "\u0283\u026ap"}], "senses": [{"definitions": ["support or have a particular interest in a romantic pairing between two characters in a fictional series, often when this relationship is one portrayed by fans rather than depicted in the series itself"], "examples": [{"text": "I'm still shipping for Edward/Hermione"}, {"notes": [{"text": "with object", "type": "grammaticalNote"}], "text": "if you ship Paul and Sarah, then you'd better avert your eyes for this next part"}], "id": "m_en_gbus0936170.007", "registers": [{"id": "informal", "text": "Informal"}], "shortDefinitions": ["support or have particular interest in romantic pairing between two characters in fictional series"]}]}], "language": "en-gb", "lexicalCategory": {"id": "verb", "text": "Verb"}, "text": "ship"}], "type": "headword", "word": "ship"}], "word": "ship"}
