{"id": "impermeable", "metadata": {"operation": "retrieve", "provider": "Oxford University Press", "schema": "RetrieveEntry"}, "results": [{"id": "impermeable", "language": "en-gb", "lexicalEntries": [{"derivatives": [{"id": "impermeability", "text": "impermeability"}], "entries": [{"etymologies": ["late 17th century: from French imperm\u00e9able, or from late Latin impermeabilis, from in- \u2018not\u2019 + permeabilis (see permeable)"], "pronunciations": [{"audioFile": "https://audio.oxforddictionaries.com/en/mp3/impermeable_gb_1_8.mp3", "dialects": ["British English"], "phoneticNotation": "IPA", "phoneticSpelling": "\u026am\u02c8p\u0259\u02d0m\u026a\u0259b(\u0259)l"}], "senses": [{"definitions": ["not allowing fluid to pass through"], "examples": [{"text": "an impermeable membrane"}], "id": "m_en_gbus0498680.005", "shortDefinitions": ["not allowing fluid to pass through"], "synonyms": [{"language": "en", "text": "watertight"}, {"language": "en", "text": "waterproof"}, {"language": "en", "text": "damp-proof"}, {"language": "en", "text": "water-resistant"}, {"language": "en", "text": "water-repellent"}, {"language": "en", "text": "airtight"}, {"language": "en", "text": "tight"}, {"language": "en", "text": "sealed"}, {"language": "en", "text": "hermetically sealed"}, {"language": "en", "text": "closed"}], "thesaurusLinks": [{"entry_id": "impermeable", "sense_id": "t_en_gb0007449.001"}]}]}], "language": "en-gb", "lexicalCategory": {"id": "adjective", "text": "Adjective"}, "text": "impermeable"}], "type": "headword", "word": "impermeable"}], "word": "impermeable"}
