{"id": "inundate", "metadata": {"operation": "retrieve", "provider": "Oxford University Press", "schema": "RetrieveEntry"}, "results": [{"id": "inundate", "language": "en-gb", "lexicalEntries": [{"entries": [{"etymologies": ["late 16th century: (earlier (late Middle English) as inundation) from Latin inundat- \u2018flooded\u2019, from the verb inundare, from in- \u2018into, upon\u2019 + undare \u2018to flow\u2019 (from unda \u2018a wave\u2019)"], "grammaticalFeatures": [{"id": "transitive", "text": "Transitive", "type": "Subcategorization"}], "pronunciations": [{"audioFile": "https://audio.oxforddictionaries.com/en/mp3/inundate_gb_1.mp3", "dialects": ["British English"], "phoneticNotation": "IPA", "phoneticSpelling": "\u02c8\u026an\u028cnde\u026at"}], "senses": [{"definitions": ["overwhelm (someone) with things or people to be dealt with"], "examples": [{"text": "we've been inundated with complaints from listeners"}], "id": "m_en_gbus0519230.006", "shortDefinitions": ["overwhelm someone with things or people to be dealt with"], "synonyms": [{"language": "en", "text": "overwhelm"}, {"language": "en", "text": "overpower"}, {"language": "en", "text": "overburden"}, {"language": "en", "text": "overrun"}, {"language": "en", "text": "overload"}, {"language": "en", "text": "swamp"}, {"language": "en", "text": "bog down"}, {"language": "en", "text": "besiege"}, {"language": "en", "text": "snow under"}, {"language": "en", "text": "bury"}, {"language": "en", "text": "bombard"}, {"language": "en", "text": "glut"}], "thesaurusLinks": [{"entry_id": "inundate", "sense_id": "t_en_gb0008151.002"}]}, {"definitions": ["flood"], "examples": [{"text": "the islands may be the first to be inundated as sea levels rise"}], "id": "m_en_gbus0519230.013", "shortDefinitions": ["flood"], "synonyms": [{"language": "en", "text": "flood"}, {"language": "en", "text": "deluge"}, {"language": "en", "text": "overflow"}, {"language": "en", "text": "overrun"}, {"language": "en", "text": "swamp"}, {"language": "en", "text": "submerge"}, {"language": "en", "text": "engulf"}, {"language": "en", "text": "drown"}, {"language": "en", "text": "immerse"}, {"language": "en", "text": "cover"}], "thesaurusLinks": [{"entry_id": "inundate", "sense_id": "t_en_gb0008151.001"}]}]}], "language": "en-gb", "lexicalCategory": {"id": "verb", "text": "Verb"}, "text": "inundate"}], "type": "headword", "word": "inundate"}], "word": "inundate"}
