{"id": "legerdemain", "metadata": {"operation": "retrieve", "provider": "Oxford University Press", "schema": "RetrieveEntry"}, "results": [{"id": "legerdemain", "language": "en-gb", "lexicalEntries": [{"entries": [{"etymologies": ["late Middle English: from French l\u00e9ger de main \u2018dexterous\u2019, literally \u2018light of hand\u2019"], "grammaticalFeatures": [{"id": "mass", "text": "Mass", "type": "Countability"}], "pronunciations": [{"audioFile": "https://audio.oxforddictionaries.com/en/mp3/legerdemain_gb_1_8.mp3", "dialects": ["British English"], "phoneticNotation": "IPA", "phoneticSpelling": "\u02ccl\u025bd\u0292\u0259d\u026a\u02c8me\u026an"}], "senses": [{"definitions": ["skilful use of one's hands when performing conjuring tricks."], "domainClasses": [{"id": "theatre", "text": "Theatre"}], "id": "m_en_gbus0573700.005", "semanticClasses": [{"id": "practice", "text": "Practice"}], "shortDefinitions": ["skilful use of one's hands when performing conjuring tricks"], "subsenses": [{"definitions": ["deception; trickery"], "examples": [{"text": "a classic piece of management legerdemain"}], "id": "m_en_gbus0573700.007", "semanticClasses": [{"id": "deception", "text": "Deception"}], "shortDefinitions": ["deception"], "synonyms": [{"language": "en", "text": "trickery"}, {"language": "en", "text": "cunning"}, {"language": "en", "text": "artfulness"}, {"language": "en", "text": "craftiness"}, {"language": "en", "text": "craft"}, {"language": "en", "text": "wiles"}, {"language": "en", "text": "chicanery"}, {"language": "en", "text": "skulduggery"}, {"language": "en", "text": "deceit"}, {"language": "en", "text": "deception"}, {"language": "en", "text": "artifice"}, {"language": "en", "text": "cheating"}, {"language": "en", "text": "dissimulation"}, {"language": "en", "text": "double-dealing"}, {"language": "en", "text": "artful argument"}, {"language": "en", "text": "specious reasoning"}, {"language": "en", "text": "sophistry"}, {"language": "en", "text": "humbug"}, {"language": "en", "text": "flimflam"}], "thesaurusLinks": [{"entry_id": "legerdemain", "sense_id": "t_en_gb0008673.002"}]}], "synonyms": [{"language": "en", "text": "sleight of hand"}, {"language": "en", "text": "juggling"}, {"language": "en", "text": "conjuring"}, {"language": "en", "text": "magic"}, {"language": "en", "text": "prestidigitation"}, {"language": "en", "text": "wizardry"}, {"language": "en", "text": "illusion"}, {"language": "en", "text": "dexterity"}], "thesaurusLinks": [{"entry_id": "legerdemain", "sense_id": "t_en_gb0008673.001"}]}]}], "language": "en-gb", "lexicalCategory": {"id": "noun", "text": "Noun"}, "text": "legerdemain"}], "type": "headword", "word": "legerdemain"}], "word": "legerdemain"}
