{"id": "levy", "metadata": {"operation": "retrieve", "provider": "Oxford University Press", "schema": "RetrieveEntry"}, "results": [{"id": "levy", "language": "en-gb", "lexicalEntries": [{"derivatives": [{"id": "leviable", "text": "leviable"}], "entries": [{"etymologies": ["Middle English (as a noun): from Old French levee, feminine past participle of lever \u2018raise\u2019, from Latin levare, from levis \u2018light\u2019"], "grammaticalFeatures": [{"id": "transitive", "text": "Transitive", "type": "Subcategorization"}], "inflections": [{"grammaticalFeatures": [{"id": "transitive", "text": "Transitive", "type": "Subcategorization"}], "inflectedForm": "levies"}, {"grammaticalFeatures": [{"id": "transitive", "text": "Transitive", "type": "Subcategorization"}], "inflectedForm": "levying"}, {"grammaticalFeatures": [{"id": "transitive", "text": "Transitive", "type": "Subcategorization"}], "inflectedForm": "levied"}], "pronunciations": [{"audioFile": "https://audio.oxforddictionaries.com/en/mp3/levy_gb_1.mp3", "dialects": ["British English"], "phoneticNotation": "IPA", "phoneticSpelling": "\u02c8l\u025bvi"}], "senses": [{"definitions": ["impose (a tax, fee, or fine)"], "domainClasses": [{"id": "politics", "text": "Politics"}], "examples": [{"text": "a tax of two per cent was levied on all cargoes"}], "id": "m_en_gbus0577960.006", "shortDefinitions": ["impose tax etc."], "subsenses": [{"definitions": ["impose a tax, fee, or fine on"], "domainClasses": [{"id": "politics", "text": "Politics"}], "examples": [{"text": "there will be powers to levy the owner"}], "id": "m_en_gbus0577960.012", "shortDefinitions": ["impose tax on"], "synonyms": [{"language": "en", "text": "impose"}, {"language": "en", "text": "charge"}, {"language": "en", "text": "exact"}, {"language": "en", "text": "demand"}, {"language": "en", "text": "raise"}, {"language": "en", "text": "collect"}, {"language": "en", "text": "gather"}], "thesaurusLinks": [{"entry_id": "levy", "sense_id": "t_en_gb0008718.001"}]}, {"definitions": ["seize (property) to satisfy a legal judgement"], "domainClasses": [{"id": "law", "text": "Law"}], "examples": [{"text": "there were no goods to levy upon"}], "id": "m_en_gbus0577960.013", "notes": [{"text": "no object", "type": "grammaticalNote"}, {"text": "\"levy on/upon\"", "type": "wordFormNote"}], "shortDefinitions": ["seize property to satisfy legal judgement"]}], "synonyms": [{"language": "en", "text": "impose"}, {"language": "en", "text": "charge"}, {"language": "en", "text": "exact"}, {"language": "en", "text": "demand"}, {"language": "en", "text": "raise"}, {"language": "en", "text": "collect"}, {"language": "en", "text": "gather"}], "thesaurusLinks": [{"entry_id": "levy", "sense_id": "t_en_gb0008718.001"}]}, {"definitions": ["enlist (someone) for military service"], "domainClasses": [{"id": "military_history", "text": "Military_History"}], "examples": [{"text": "he sought to levy one man from each vill for service"}], "id": "m_en_gbus0577960.015", "registers": [{"id": "archaic", "text": "Archaic"}], "shortDefinitions": ["enlist for military service"], "subsenses": [{"definitions": ["begin to wage (war)"], "examples": [{"text": "they then proceeded without further ceremony to levy war upon the king"}], "id": "m_en_gbus0577960.016", "shortDefinitions": ["begin to wage war"]}], "synonyms": [{"language": "en", "text": "conscript"}, {"language": "en", "text": "call up"}, {"language": "en", "text": "enlist"}, {"language": "en", "text": "mobilize"}, {"language": "en", "text": "rally"}, {"language": "en", "text": "muster"}, {"language": "en", "text": "marshal"}, {"language": "en", "text": "press"}, {"language": "en", "text": "recruit"}, {"language": "en", "text": "raise"}, {"language": "en", "text": "assemble"}, {"language": "en", "text": "round up"}], "thesaurusLinks": [{"entry_id": "levy", "sense_id": "t_en_gb0008718.002"}]}]}], "language": "en-gb", "lexicalCategory": {"id": "verb", "text": "Verb"}, "text": "levy"}, {"derivatives": [{"id": "leviable", "text": "leviable"}], "entries": [{"inflections": [{"grammaticalFeatures": [{"id": "plural", "text": "Plural", "type": "Number"}], "inflectedForm": "levies"}], "pronunciations": [{"audioFile": "https://audio.oxforddictionaries.com/en/mp3/levy_gb_1.mp3", "dialects": ["British English"], "phoneticNotation": "IPA", "phoneticSpelling": "\u02c8l\u025bvi"}], "senses": [{"constructions": [{"text": "levy on"}], "definitions": ["an act of levying a tax, fee, or fine"], "domainClasses": [{"id": "economics", "text": "Economics"}], "examples": [{"text": "police forces receive 49 per cent of their funding via a levy on the rates"}], "id": "m_en_gbus0577960.019", "semanticClasses": [{"id": "action", "text": "Action"}], "shortDefinitions": ["act of levying tax etc."], "subsenses": [{"definitions": ["a tax raised by levying"], "domainClasses": [{"id": "economics", "text": "Economics"}], "examples": [{"text": "we all pay a fossil fuel levy in our electricity bills"}], "id": "m_en_gbus0577960.022", "semanticClasses": [{"id": "tax", "text": "Tax"}], "shortDefinitions": ["tax raised by levying"], "synonyms": [{"language": "en", "text": "tax"}, {"language": "en", "text": "levy"}, {"language": "en", "text": "tariff"}, {"language": "en", "text": "excise"}, {"language": "en", "text": "toll"}, {"language": "en", "text": "fee"}, {"language": "en", "text": "imposition"}, {"language": "en", "text": "impost"}, {"language": "en", "text": "exaction"}, {"language": "en", "text": "tithe"}, {"language": "en", "text": "payment"}, {"language": "en", "text": "rate"}], "thesaurusLinks": [{"entry_id": "duty", "sense_id": "t_en_gb0004554.003"}]}, {"definitions": ["a sum collected as a supplement to an existing subscription"], "domainClasses": [{"id": "politics", "text": "Politics"}], "examples": [{"text": "the trade-union political levy"}], "id": "m_en_gbus0577960.023", "semanticClasses": [{"id": "payment", "text": "Payment"}], "shortDefinitions": ["sum collected as supplement to subscription"], "synonyms": [{"language": "en", "text": "imposition"}, {"language": "en", "text": "charging"}, {"language": "en", "text": "exaction"}, {"language": "en", "text": "raising"}, {"language": "en", "text": "collection"}, {"language": "en", "text": "gathering"}], "thesaurusLinks": [{"entry_id": "levy", "sense_id": "t_en_gb0008718.003"}]}, {"definitions": ["an item or items of property seized to satisfy a legal judgement."], "domainClasses": [{"id": "law", "text": "Law"}], "id": "m_en_gbus0577960.024", "semanticClasses": [{"id": "property", "text": "Property"}], "shortDefinitions": ["property seized to satisfy legal judgement"]}], "synonyms": [{"language": "en", "text": "tax"}, {"language": "en", "text": "tariff"}, {"language": "en", "text": "toll"}, {"language": "en", "text": "excise"}, {"language": "en", "text": "duty"}, {"language": "en", "text": "fee"}, {"language": "en", "text": "imposition"}, {"language": "en", "text": "impost"}, {"language": "en", "text": "exaction"}, {"language": "en", "text": "assessment"}, {"language": "en", "text": "tithe"}, {"language": "en", "text": "payment"}], "thesaurusLinks": [{"entry_id": "levy", "sense_id": "t_en_gb0008718.004"}]}, {"definitions": ["an act of enlisting troops"], "domainClasses": [{"id": "military_history", "text": "Military_History"}], "examples": [{"text": "Edward I and Edward II had made substantial use of the feudal levy for raising an army"}], "id": "m_en_gbus0577960.026", "registers": [{"id": "historical", "text": "Historical"}], "semanticClasses": [{"id": "recruitment", "text": "Recruitment"}], "shortDefinitions": ["act of enlisting troops"], "subsenses": [{"definitions": ["a body of troops that have been enlisted"], "domainClasses": [{"id": "military_history", "text": "Military_History"}], "examples": [{"text": "lightly armed local levies"}], "id": "m_en_gbus0577960.027", "notes": [{"text": "usually \"levies\"", "type": "wordFormNote"}], "semanticClasses": [{"id": "military_unit", "text": "Military_Unit"}], "shortDefinitions": ["body of enlisted troops"], "synonyms": [{"language": "en", "text": "conscripts"}, {"language": "en", "text": "militia"}], "thesaurusLinks": [{"entry_id": "levy", "sense_id": "t_en_gb0008718.005"}]}]}]}], "language": "en-gb", "lexicalCategory": {"id": "noun", "text": "Noun"}, "text": "levy"}], "type": "headword", "word": "levy"}], "word": "levy"}
