{"id": "orison", "metadata": {"operation": "retrieve", "provider": "Oxford University Press", "schema": "RetrieveEntry"}, "results": [{"id": "orison", "language": "en-gb", "lexicalEntries": [{"entries": [{"etymologies": ["Middle English: from Old French oreison, from Latin oratio(n-) \u2018speech\u2019 (see oration)"], "notes": [{"text": "usually \"orisons\"", "type": "wordFormNote"}], "pronunciations": [{"audioFile": "https://audio.oxforddictionaries.com/en/mp3/orison_gb_1_8.mp3", "dialects": ["British English"], "phoneticNotation": "IPA", "phoneticSpelling": "\u02c8\u0252r\u026az(\u0259)n"}, {"dialects": ["British English"], "phoneticNotation": "IPA", "phoneticSpelling": "\u02c8\u0252r\u026as(\u0259)n"}], "senses": [{"definitions": ["a prayer."], "id": "m_en_gbus0727010.011", "registers": [{"id": "archaic", "text": "Archaic"}], "semanticClasses": [{"id": "prayer", "text": "Prayer"}], "shortDefinitions": ["prayer"], "synonyms": [{"language": "en", "text": "entreaty"}, {"language": "en", "text": "plea"}, {"language": "en", "text": "appeal"}, {"language": "en", "text": "petition"}, {"language": "en", "text": "solicitation"}, {"language": "en", "text": "exhortation"}, {"language": "en", "text": "urge"}, {"language": "en", "text": "prayer"}, {"language": "en", "text": "invocation"}, {"language": "en", "text": "suit"}, {"language": "en", "text": "request"}, {"language": "en", "text": "application"}], "thesaurusLinks": [{"entry_id": "supplication", "sense_id": "t_en_gb0014446.001"}]}]}], "language": "en-gb", "lexicalCategory": {"id": "noun", "text": "Noun"}, "text": "orison"}], "type": "headword", "word": "orison"}], "word": "orison"}
