{"id": "belligerent", "metadata": {"operation": "retrieve", "provider": "Oxford University Press", "schema": "RetrieveEntry"}, "results": [{"id": "belligerent", "language": "en-gb", "lexicalEntries": [{"derivatives": [{"id": "belligerently", "text": "belligerently"}], "entries": [{"etymologies": ["late 16th century: from Latin belligerant- \u2018waging war\u2019, from the verb belligerare, from bellum \u2018war\u2019"], "pronunciations": [{"audioFile": "https://audio.oxforddictionaries.com/en/mp3/belligerent_gb_1.mp3", "dialects": ["British English"], "phoneticNotation": "IPA", "phoneticSpelling": "b\u0259\u02c8l\u026ad\u0292(\u0259)r(\u0259)nt"}], "senses": [{"definitions": ["hostile and aggressive"], "examples": [{"text": "the mood at the meeting was belligerent"}], "id": "m_en_gbus0085700.005", "shortDefinitions": ["hostile and aggressive"], "subsenses": [{"definitions": ["engaged in a war or conflict, as recognized by international law"], "domainClasses": [{"id": "law", "text": "Law"}], "examples": [{"text": "after years of mass slaughter and hardship, opposition to the war became widespread in all the belligerent countries"}], "id": "m_en_gbus0085700.007", "shortDefinitions": ["engaged in war or conflict, as recognized by international law"], "synonyms": [{"language": "en", "text": "warring"}, {"language": "en", "text": "at war"}, {"language": "en", "text": "combatant"}, {"language": "en", "text": "fighting"}, {"language": "en", "text": "battling"}, {"language": "en", "text": "contending"}, {"language": "en", "text": "conflicting"}, {"language": "en", "text": "clashing"}, {"language": "en", "text": "quarrelling"}], "thesaurusLinks": [{"entry_id": "belligerent", "sense_id": "t_en_gb0001325.002"}]}], "synonyms": [{"language": "en", "text": "hostile"}, {"language": "en", "text": "aggressive"}, {"language": "en", "text": "threatening"}, {"language": "en", "text": "antagonistic"}, {"language": "en", "text": "pugnacious"}, {"language": "en", "text": "bellicose"}, {"language": "en", "text": "truculent"}, {"language": "en", "text": "confrontational"}, {"language": "en", "text": "argumentative"}, {"language": "en", "text": "quarrelsome"}, {"language": "en", "text": "disputatious"}, {"language": "en", "text": "contentious"}, {"language": "en", "text": "militant"}, {"language": "en", "text": "combative"}], "thesaurusLinks": [{"entry_id": "belligerent", "sense_id": "t_en_gb0001325.001"}]}]}], "language": "en-gb", "lexicalCategory": {"id": "adjective", "text": "Adjective"}, "text": "belligerent"}, {"derivatives": [{"id": "belligerently", "text": "belligerently"}], "entries": [{"pronunciations": [{"audioFile": "https://audio.oxforddictionaries.com/en/mp3/belligerent_gb_1.mp3", "dialects": ["British English"], "phoneticNotation": "IPA", "phoneticSpelling": "b\u0259\u02c8l\u026ad\u0292(\u0259)r(\u0259)nt"}], "senses": [{"definitions": ["a nation or person engaged in war or conflict, as recognized by international law"], "domainClasses": [{"id": "law", "text": "Law"}], "examples": [{"text": "ships and goods captured at sea by a belligerent"}], "id": "m_en_gbus0085700.009", "semanticClasses": [{"id": "nation", "text": "Nation"}], "shortDefinitions": ["nation or person engaged in war or conflict"], "synonyms": [{"language": "en", "text": "militarist"}, {"language": "en", "text": "hawk"}, {"language": "en", "text": "jingoist"}, {"language": "en", "text": "sabre-rattler"}, {"language": "en", "text": "aggressor"}, {"language": "en", "text": "provoker"}, {"language": "en", "text": "belligerent"}], "thesaurusLinks": [{"entry_id": "warmonger", "sense_id": "t_en_gb0016099.001"}]}]}], "language": "en-gb", "lexicalCategory": {"id": "noun", "text": "Noun"}, "text": "belligerent"}], "type": "headword", "word": "belligerent"}], "word": "belligerent"}
