{"id": "tocsin", "metadata": {"operation": "retrieve", "provider": "Oxford University Press", "schema": "RetrieveEntry"}, "results": [{"id": "tocsin", "language": "en-gb", "lexicalEntries": [{"entries": [{"etymologies": ["late 16th century: from Old French toquassen, from Proven\u00e7al tocasenh, from tocar \u2018to touch\u2019 + senh \u2018signal bell\u2019"], "pronunciations": [{"audioFile": "https://audio.oxforddictionaries.com/en/mp3/tocsin_gb_1.mp3", "dialects": ["British English"], "phoneticNotation": "IPA", "phoneticSpelling": "\u02c8t\u0252ks\u026an"}], "senses": [{"definitions": ["an alarm bell or signal"], "examples": [{"text": "he used his resignation as a tocsin to warn of the danger of dictatorship"}], "id": "m_en_gbus1058430.007", "registers": [{"id": "archaic", "text": "Archaic"}], "semanticClasses": [{"id": "signal", "text": "Signal"}], "shortDefinitions": ["alarm bell or signal"], "synonyms": [{"language": "en", "text": "ringing"}, {"language": "en", "text": "chime"}, {"language": "en", "text": "carillon"}, {"language": "en", "text": "toll"}, {"language": "en", "text": "tolling"}, {"language": "en", "text": "peal"}, {"language": "en", "text": "knell"}], "thesaurusLinks": [{"entry_id": "ring", "sense_id": "t_en_gb0012656.006"}]}]}], "language": "en-gb", "lexicalCategory": {"id": "noun", "text": "Noun"}, "text": "tocsin"}], "type": "headword", "word": "tocsin"}], "word": "tocsin"}
