{"id": "bequest", "metadata": {"operation": "retrieve", "provider": "Oxford University Press", "schema": "RetrieveEntry"}, "results": [{"id": "bequest", "language": "en-gb", "lexicalEntries": [{"entries": [{"etymologies": ["Middle English: from be-\u2018about\u2019 + Old English cwis \u2018speech\u2019, influenced by bequeath"], "pronunciations": [{"audioFile": "https://audio.oxforddictionaries.com/en/mp3/bequest_gb_1.mp3", "dialects": ["British English"], "phoneticNotation": "IPA", "phoneticSpelling": "b\u026a\u02c8kw\u025bst"}], "senses": [{"definitions": ["a legacy"], "examples": [{"text": "a bequest of over \u00a3300,000"}], "id": "m_en_gbus0087960.005", "semanticClasses": [{"id": "legacy", "text": "Legacy"}], "shortDefinitions": ["legacy"], "subsenses": [{"definitions": ["the action of bequeathing something"], "examples": [{"text": "a painting acquired by bequest"}], "id": "m_en_gbus0087960.008", "notes": [{"text": "mass noun", "type": "grammaticalNote"}], "semanticClasses": [{"id": "action", "text": "Action"}], "shortDefinitions": ["action of bequeathing something"], "synonyms": [{"language": "en", "text": "donation"}, {"language": "en", "text": "gift"}, {"language": "en", "text": "benefaction"}, {"language": "en", "text": "offering"}, {"language": "en", "text": "present"}, {"language": "en", "text": "handout"}], "thesaurusLinks": [{"entry_id": "contribution", "sense_id": "t_en_gb0002969.001"}]}], "synonyms": [{"language": "en", "text": "legacy"}, {"language": "en", "text": "inheritance"}, {"language": "en", "text": "endowment"}, {"language": "en", "text": "estate"}, {"language": "en", "text": "heritage"}, {"language": "en", "text": "bestowal"}, {"language": "en", "text": "bequeathal"}, {"language": "en", "text": "settlement"}, {"language": "en", "text": "provision"}, {"language": "en", "text": "benefaction"}, {"language": "en", "text": "gift"}, {"language": "en", "text": "present"}, {"language": "en", "text": "contribution"}, {"language": "en", "text": "donation"}], "thesaurusLinks": [{"entry_id": "bequest", "sense_id": "t_en_gb0001355.001"}]}]}], "language": "en-gb", "lexicalCategory": {"id": "noun", "text": "Noun"}, "text": "bequest"}], "type": "headword", "word": "bequest"}], "word": "bequest"}
