{"id": "diverge", "metadata": {"operation": "retrieve", "provider": "Oxford University Press", "schema": "RetrieveEntry"}, "results": [{"id": "diverge", "language": "en-gb", "lexicalEntries": [{"entries": [{"etymologies": ["mid 17th century: from medieval Latin divergere, from Latin dis- \u2018in two ways\u2019 + vergere \u2018to turn or incline\u2019"], "grammaticalFeatures": [{"id": "intransitive", "text": "Intransitive", "type": "Subcategorization"}], "pronunciations": [{"audioFile": "https://audio.oxforddictionaries.com/en/mp3/diverge_gb_1.mp3", "dialects": ["British English"], "phoneticNotation": "IPA", "phoneticSpelling": "d\u028c\u026a\u02c8v\u0259\u02d0d\u0292"}, {"dialects": ["British English"], "phoneticNotation": "IPA", "phoneticSpelling": "d\u026a\u02c8v\u0259\u02d0d\u0292"}], "senses": [{"definitions": ["(of a road, route, or line) separate from another route and go in a different direction"], "examples": [{"text": "the flight path diverged from the original flight plan"}, {"registers": [{"id": "figurative", "text": "Figurative"}], "text": "their ways had diverged at university"}], "id": "m_en_gbus0285330.009", "shortDefinitions": ["separate and go in different direction"], "subsenses": [{"definitions": ["(of an opinion, theory, or approach) differ"], "examples": [{"text": "the coverage by the columnists diverged from that in the main news stories"}], "id": "m_en_gbus0285330.019", "shortDefinitions": ["(of opinion etc.) differ"], "synonyms": [{"language": "en", "text": "differ"}, {"language": "en", "text": "be different"}, {"language": "en", "text": "be unlike"}, {"language": "en", "text": "be dissimilar"}], "thesaurusLinks": [{"entry_id": "diverge", "sense_id": "t_en_gb0004302.002"}]}, {"definitions": ["depart from (a set course or standard)"], "examples": [{"text": "suddenly he diverged from his text"}], "id": "m_en_gbus0285330.020", "notes": [{"text": "\"diverge from\"", "type": "wordFormNote"}], "shortDefinitions": ["depart from set course or standard"], "synonyms": [{"language": "en", "text": "deviate"}, {"language": "en", "text": "digress"}, {"language": "en", "text": "depart"}, {"language": "en", "text": "veer"}, {"language": "en", "text": "swerve"}, {"language": "en", "text": "turn away"}, {"language": "en", "text": "turn aside"}, {"language": "en", "text": "branch off"}, {"language": "en", "text": "drift"}, {"language": "en", "text": "stray"}], "thesaurusLinks": [{"entry_id": "diverge", "sense_id": "t_en_gb0004302.003"}]}, {"definitions": ["develop in a different direction"], "examples": [{"text": "English Gothic architecture began to diverge from that on the Continent"}], "id": "m_en_gbus0285330.021", "shortDefinitions": ["develop differently"]}], "synonyms": [{"language": "en", "text": "separate"}, {"language": "en", "text": "part"}, {"language": "en", "text": "disunite"}, {"language": "en", "text": "fork"}, {"language": "en", "text": "branch off"}, {"language": "en", "text": "divide"}, {"language": "en", "text": "subdivide"}, {"language": "en", "text": "split"}, {"language": "en", "text": "go in different directions"}, {"language": "en", "text": "go separate ways"}], "thesaurusLinks": [{"entry_id": "diverge", "sense_id": "t_en_gb0004302.001"}]}, {"definitions": ["(of a series) increase indefinitely as more of its terms are added."], "domainClasses": [{"id": "mathematics", "text": "Mathematics"}], "domains": [{"id": "mathematics", "text": "Mathematics"}], "id": "m_en_gbus0285330.023", "shortDefinitions": ["(of series) increase indefinitely"]}]}], "language": "en-gb", "lexicalCategory": {"id": "verb", "text": "Verb"}, "text": "diverge"}], "type": "headword", "word": "diverge"}], "word": "diverge"}
