{"id": "extant", "metadata": {"operation": "retrieve", "provider": "Oxford University Press", "schema": "RetrieveEntry"}, "results": [{"id": "extant", "language": "en-gb", "lexicalEntries": [{"entries": [{"etymologies": ["mid 16th century (in the sense \u2018able to be publicly seen or reached\u2019): from Latin exstant- \u2018being visible or prominent, existing\u2019, from the verb exstare, from ex- \u2018out\u2019 + stare \u2018to stand\u2019"], "pronunciations": [{"audioFile": "https://audio.oxforddictionaries.com/en/mp3/extant_gb_1_8.mp3", "dialects": ["British English"], "phoneticNotation": "IPA", "phoneticSpelling": "\u026ak\u02c8stant"}, {"dialects": ["British English"], "phoneticNotation": "IPA", "phoneticSpelling": "\u025bk\u02c8stant"}, {"audioFile": "https://audio.oxforddictionaries.com/en/mp3/extant_gb_2.mp3", "dialects": ["British English"], "phoneticNotation": "IPA", "phoneticSpelling": "\u02c8\u025bkst(\u0259)nt"}], "senses": [{"definitions": ["still in existence; surviving"], "examples": [{"text": "an extant letter"}], "id": "m_en_gbus0343550.009", "shortDefinitions": ["still in existence"], "synonyms": [{"language": "en", "text": "still existing"}, {"language": "en", "text": "in existence"}, {"language": "en", "text": "surviving"}, {"language": "en", "text": "remaining"}, {"language": "en", "text": "abiding"}, {"language": "en", "text": "enduring"}, {"language": "en", "text": "undestroyed"}, {"language": "en", "text": "present"}, {"language": "en", "text": "existent"}], "thesaurusLinks": [{"entry_id": "extant", "sense_id": "t_en_gb0005327.001"}]}]}], "language": "en-gb", "lexicalCategory": {"id": "adjective", "text": "Adjective"}, "text": "extant"}], "type": "headword", "word": "extant"}], "word": "extant"}
