{"id": "fallacious", "metadata": {"operation": "retrieve", "provider": "Oxford University Press", "schema": "RetrieveEntry"}, "results": [{"id": "fallacious", "language": "en-gb", "lexicalEntries": [{"derivatives": [{"id": "fallaciously", "text": "fallaciously"}, {"id": "fallaciousness", "text": "fallaciousness"}], "entries": [{"etymologies": ["late 15th century: from Old French fallacieux, from Latin fallaciosus, from fallacia (see fallacy)"], "pronunciations": [{"audioFile": "https://audio.oxforddictionaries.com/en/mp3/fallacious_gb_1.mp3", "dialects": ["British English"], "phoneticNotation": "IPA", "phoneticSpelling": "f\u0259\u02c8le\u026a\u0283\u0259s"}], "senses": [{"definitions": ["based on a mistaken belief"], "examples": [{"text": "fallacious arguments"}], "id": "m_en_gbus0348630.005", "shortDefinitions": ["based on mistaken belief"], "synonyms": [{"language": "en", "text": "erroneous"}, {"language": "en", "text": "false"}, {"language": "en", "text": "untrue"}, {"language": "en", "text": "wrong"}, {"language": "en", "text": "incorrect"}, {"language": "en", "text": "faulty"}, {"language": "en", "text": "flawed"}, {"language": "en", "text": "inaccurate"}, {"language": "en", "text": "inexact"}, {"language": "en", "text": "imprecise"}, {"language": "en", "text": "mistaken"}, {"language": "en", "text": "misinformed"}, {"language": "en", "text": "misguided"}, {"language": "en", "text": "misleading"}, {"language": "en", "text": "deceptive"}, {"language": "en", "text": "delusive"}, {"language": "en", "text": "delusory"}, {"language": "en", "text": "illusory"}, {"language": "en", "text": "sophistic"}, {"language": "en", "text": "specious"}, {"language": "en", "text": "fictitious"}, {"language": "en", "text": "spurious"}, {"language": "en", "text": "fabricated"}, {"language": "en", "text": "distorted"}, {"language": "en", "text": "made up"}, {"language": "en", "text": "trumped up"}], "thesaurusLinks": [{"entry_id": "fallacious", "sense_id": "t_en_gb0005437.001"}]}]}], "language": "en-gb", "lexicalCategory": {"id": "adjective", "text": "Adjective"}, "text": "fallacious"}], "type": "headword", "word": "fallacious"}], "word": "fallacious"}
