{"id": "geo", "metadata": {"operation": "retrieve", "provider": "Oxford University Press", "schema": "RetrieveEntry"}, "results": [{"id": "geo", "language": "en-gb", "lexicalEntries": [{"entries": [{"etymologies": ["early 17th century (originally Orkney and Shetland dialect): from Old Norse gj\u00e1"], "inflections": [{"grammaticalFeatures": [{"id": "plural", "text": "Plural", "type": "Number"}], "inflectedForm": "geos"}], "pronunciations": [{"audioFile": "https://audio.oxforddictionaries.com/en/mp3/geo_gb_1.mp3", "dialects": ["British English"], "phoneticNotation": "IPA", "phoneticSpelling": "\u0261j\u0259\u028a"}, {"audioFile": "https://audio.oxforddictionaries.com/en/mp3/geo_gb_2.mp3", "dialects": ["British English"], "phoneticNotation": "IPA", "phoneticSpelling": "\u02c8d\u0292i\u02d0\u0259\u028a"}], "senses": [{"definitions": ["a long, narrow, steep-sided cleft formed by erosion in coastal cliffs."], "domainClasses": [{"id": "geography", "text": "Geography"}], "id": "m_en_gbus0409790.004", "semanticClasses": [{"id": "depression", "text": "Depression"}], "shortDefinitions": ["cleft formed by erosion in coastal cliffs"]}]}], "language": "en-gb", "lexicalCategory": {"id": "noun", "text": "Noun"}, "text": "geo"}], "type": "headword", "word": "geo"}], "word": "geo"}
