{"id": "muffler", "metadata": {"operation": "retrieve", "provider": "Oxford University Press", "schema": "RetrieveEntry"}, "results": [{"id": "muffler", "language": "en-gb", "lexicalEntries": [{"entries": [{"pronunciations": [{"audioFile": "https://audio.oxforddictionaries.com/en/mp3/muffler_gb_1.mp3", "dialects": ["British English"], "phoneticNotation": "IPA", "phoneticSpelling": "\u02c8m\u028cfl\u0259"}], "senses": [{"definitions": ["a wrap or scarf worn around the neck and face for warmth."], "domainClasses": [{"id": "clothing", "text": "Clothing"}], "id": "m_en_gbus0667620.006", "semanticClasses": [{"id": "garment", "text": "Garment"}], "shortDefinitions": ["wrap or scarf worn around neck and face for warmth"]}, {"definitions": ["a device used to deaden the sound of a drum, bell, piano, or other instrument."], "domainClasses": [{"id": "music", "text": "Music"}], "id": "m_en_gbus0667620.010", "semanticClasses": [{"id": "instrument_part", "text": "Instrument_Part"}], "shortDefinitions": ["device used to deaden sound of instrument"], "subsenses": [{"definitions": ["a device fixed to the exhaust of a motor vehicle to reduce engine noise; a silencer."], "domainClasses": [{"id": "mechanics", "text": "Mechanics"}, {"id": "motoring", "text": "Motoring"}], "id": "m_en_gbus0667620.011", "regions": [{"id": "north_american", "text": "North_American"}], "semanticClasses": [{"id": "device", "text": "Device"}], "shortDefinitions": ["silencer for motor vehicle exhaust"]}]}]}], "language": "en-gb", "lexicalCategory": {"id": "noun", "text": "Noun"}, "text": "muffler"}], "type": "headword", "word": "muffler"}], "word": "muffler"}
