{"id": "bursary", "metadata": {"operation": "retrieve", "provider": "Oxford University Press", "schema": "RetrieveEntry"}, "results": [{"id": "bursary", "language": "en-gb", "lexicalEntries": [{"derivatives": [{"id": "bursarial", "text": "bursarial"}], "entries": [{"etymologies": ["late 17th century (in bursary (sense 2)): from medieval Latin bursaria, from bursa \u2018bag, purse\u2019 (see bursa)"], "inflections": [{"grammaticalFeatures": [{"id": "plural", "text": "Plural", "type": "Number"}], "inflectedForm": "bursaries"}], "pronunciations": [{"audioFile": "https://audio.oxforddictionaries.com/en/mp3/bursary_gb_1.mp3", "dialects": ["British English"], "phoneticNotation": "IPA", "phoneticSpelling": "\u02c8b\u0259\u02d0s\u0259ri"}], "senses": [{"definitions": ["a grant, especially one awarded to someone to enable them to study at university or college."], "domainClasses": [{"id": "university", "text": "University"}], "id": "m_en_gbus0136870.006", "regions": [{"id": "british", "text": "British"}], "semanticClasses": [{"id": "payment", "text": "Payment"}], "shortDefinitions": ["grant awarded to someone to enable them to study at university"], "synonyms": [{"language": "en", "text": "grant"}, {"language": "en", "text": "allowance"}, {"language": "en", "text": "endowment"}, {"language": "en", "text": "contribution"}, {"language": "en", "text": "donation"}, {"language": "en", "text": "bursary"}, {"language": "en", "text": "gift"}, {"language": "en", "text": "present"}, {"language": "en", "text": "investment"}, {"language": "en", "text": "bestowal"}, {"language": "en", "text": "benefaction"}, {"language": "en", "text": "allocation"}, {"language": "en", "text": "allotment"}, {"language": "en", "text": "handout"}], "thesaurusLinks": [{"entry_id": "subsidy", "sense_id": "t_en_gb0014330.001"}]}, {"definitions": ["the room of a bursar in a college or school."], "domainClasses": [{"id": "university", "text": "University"}], "id": "m_en_gbus0136870.010", "regions": [{"id": "british", "text": "British"}], "semanticClasses": [{"id": "office", "text": "Office"}], "shortDefinitions": ["room of bursar in college or school"]}]}], "language": "en-gb", "lexicalCategory": {"id": "noun", "text": "Noun"}, "text": "bursary"}], "type": "headword", "word": "bursary"}], "word": "bursary"}
