{"id": "livid", "metadata": {"operation": "retrieve", "provider": "Oxford University Press", "schema": "RetrieveEntry"}, "results": [{"id": "livid", "language": "en-gb", "lexicalEntries": [{"derivatives": [{"id": "lividity", "text": "lividity"}, {"id": "lividly", "text": "lividly"}, {"id": "lividness", "text": "lividness"}], "entries": [{"etymologies": ["late Middle English (in the sense \u2018of a bluish leaden colour\u2019): from French livide or Latin lividus, from livere \u2018be bluish\u2019. The sense \u2018furiously angry\u2019 dates from the early 20th century"], "pronunciations": [{"audioFile": "https://audio.oxforddictionaries.com/en/mp3/livid_gb_2.mp3", "dialects": ["British English"], "phoneticNotation": "IPA", "phoneticSpelling": "\u02c8l\u026av\u026ad"}], "senses": [{"definitions": ["furiously angry"], "examples": [{"text": "he was livid that Garry had escaped"}], "id": "m_en_gbus0588410.006", "shortDefinitions": ["furiously angry"], "synonyms": [{"language": "en", "text": "furious"}, {"language": "en", "text": "angry"}, {"language": "en", "text": "infuriated"}, {"language": "en", "text": "irate"}, {"language": "en", "text": "fuming"}, {"language": "en", "text": "raging"}, {"language": "en", "text": "seething"}, {"language": "en", "text": "incensed"}, {"language": "en", "text": "enraged"}, {"language": "en", "text": "angered"}, {"language": "en", "text": "beside oneself"}, {"language": "en", "text": "wrathful"}, {"language": "en", "text": "ireful"}, {"language": "en", "text": "maddened"}, {"language": "en", "text": "cross"}, {"language": "en", "text": "annoyed"}, {"language": "en", "text": "irritated"}, {"language": "en", "text": "exasperated"}, {"language": "en", "text": "indignant"}], "thesaurusLinks": [{"entry_id": "livid", "sense_id": "t_en_gb0008848.001"}]}, {"definitions": ["dark bluish grey in colour"], "examples": [{"text": "livid bruises"}], "id": "m_en_gbus0588410.009", "shortDefinitions": ["dark bluish grey in colour"], "synonyms": [{"language": "en", "text": "purplish"}, {"language": "en", "text": "bluish"}, {"language": "en", "text": "dark"}, {"language": "en", "text": "discoloured"}, {"language": "en", "text": "black and blue"}, {"language": "en", "text": "purple"}, {"language": "en", "text": "greyish blue"}], "thesaurusLinks": [{"entry_id": "livid", "sense_id": "t_en_gb0008848.002"}]}]}], "language": "en-gb", "lexicalCategory": {"id": "adjective", "text": "Adjective"}, "text": "livid"}], "type": "headword", "word": "livid"}], "word": "livid"}
